Metadata-Version: 2.1
Name: test-native-core-dsk
Version: 0.1
Summary: Native Python SDK
Home-page: https://github.com/user/andreassujono
Download-URL: https://github.com/user/andreassujono/archive/v_01.tar.gz
Author: Andreas Sujono
Author-email: andreas.sujono@altonomy.com
License: MIT
Keywords: SOME,MEANINGFULL,KEYWORDS
Classifier: Development Status :: 3 - Alpha
Classifier: Intended Audience :: Developers
Classifier: Topic :: Software Development :: Build Tools
Classifier: License :: OSI Approved :: MIT License
Classifier: Programming Language :: Python :: 3
Classifier: Programming Language :: Python :: 3.4
Classifier: Programming Language :: Python :: 3.5
Classifier: Programming Language :: Python :: 3.6
Classifier: Programming Language :: Python :: 3.7
Classifier: Programming Language :: Python :: 3.8
Classifier: Programming Language :: Python :: 3.9
License-File: LICENSE.txt
